opengeode/AdaGenerator.py
opengeode/Asn1scc.py
opengeode/CGenerator.py
opengeode/Clipboard.py
opengeode/Connectors.py
opengeode/Helper.py
opengeode/Lander.py
opengeode/LlvmGenerator.py
opengeode/Pr.py
opengeode/QGenSDL.py
opengeode/Renderer.py
opengeode/Statechart.py
opengeode/StgBackend.py
opengeode/TextInteraction.py
opengeode/__init__.py
opengeode/genericSymbols.py
opengeode/icons.py
opengeode/ogAST.py
opengeode/ogASTDumper.py
opengeode/ogParser.py
opengeode/opengeode.py
opengeode/sdl92Lexer.py
opengeode/sdl92Parser.py
opengeode/sdlHelp.py
opengeode/sdlSymbols.py
opengeode/undoCommands.py
opengeode/version.py
opengeode-4.3.8.dist-info/LICENSE
opengeode-4.3.8.dist-info/METADATA
opengeode-4.3.8.dist-info/WHEEL
opengeode-4.3.8.dist-info/entry_points.txt
opengeode-4.3.8.dist-info/top_level.txt
opengeode-4.3.8.dist-info/RECORD
