Metadata-Version: 2.1
Name: opengeode
Version: 4.3.8
Summary: A free SDL editor for TASTE
Home-page: http://opengeode.net
Author: Maxime Perrotin
Author-email: maxime.perrotin@esa.int
Classifier: Programming Language :: Python
Classifier: License :: OSI Approved :: GNU Lesser General Public License v3 (LGPLv3)
Classifier: Operating System :: OS Independent
Classifier: Programming Language :: Python :: 3
Requires-Python: >=3.7
License-File: LICENSE
Requires-Dist: pyside6
